hpimon/FieldTrip.py
hpimon/__init__.py
hpimon/config.py
hpimon/default.cfg
hpimon/defaultconfig.py
hpimon/elekta.py
hpimon/hpimon.py
hpimon/hpimon.ui
hpimon/rt_server.py
hpimon/utils.py
hpimon-0.12.6.dist-info/DESCRIPTION.rst
hpimon-0.12.6.dist-info/METADATA
hpimon-0.12.6.dist-info/RECORD
hpimon-0.12.6.dist-info/WHEEL
hpimon-0.12.6.dist-info/entry_points.txt
hpimon-0.12.6.dist-info/metadata.json
hpimon-0.12.6.dist-info/top_level.txt
