Metadata-Version: 2.0
Name: hpimon
Version: 0.12.6
Summary: Continuous HPI monitor for Elekta MEG systems
Home-page: https://github.com/jjnurminen/hpimon
Author: Jussi Nurminen
Author-email: jnu@iki.fi
License: MIT
Platform: UNKNOWN
